digsig/__init__.py
digsig/auto.py
digsig/digsig.py
digsig/ecdsa.py
digsig/errors.py
digsig/hashing.py
digsig/rsa.py
digsig/utils.py
digsig/__pycache__/__init__.cpython-39.pyc
digsig/__pycache__/auto.cpython-39.pyc
digsig/__pycache__/digsig.cpython-39.pyc
digsig/__pycache__/ecdsa.cpython-39.pyc
digsig/__pycache__/errors.cpython-39.pyc
digsig/__pycache__/hashing.cpython-39.pyc
digsig/__pycache__/rsa.cpython-39.pyc
digsig/__pycache__/utils.cpython-39.pyc
digsig-1.216.0.dist-info/LICENSE
digsig-1.216.0.dist-info/METADATA
digsig-1.216.0.dist-info/WHEEL
digsig-1.216.0.dist-info/top_level.txt
digsig-1.216.0.dist-info/RECORD
