Metadata-Version: 2.1
Name: digsig
Version: 1.216.0
Summary: Digital signature toolkit for Python
Home-page: https://github.com/labteral/digsig
Author: Rodrigo Martínez Castaño
Author-email: rodrigo@martinez.gal
License: GNU General Public License v3 (GPLv3)
Platform: UNKNOWN
Classifier: Development Status :: 4 - Beta
Classifier: Environment :: Console
Classifier: Intended Audience :: Developers
Classifier: License :: OSI Approved :: GNU General Public License v3 (GPLv3)
Classifier: Operating System :: POSIX :: Linux
Classifier: Programming Language :: Python :: 3.6
Classifier: Programming Language :: Python :: Implementation :: PyPy
Classifier: Topic :: Software Development :: Libraries :: Python Modules
Requires-Python: >=3.6
Requires-Dist: cryptography (~=3.4.4)
Requires-Dist: eth-account (<1.0.0,>=0.5.4)
